wasm/__init__.py
wasm/__main__.py
wasm/main.py
wasm/cli/__init__.py
wasm/cli/interactive.py
wasm/cli/parser.py
wasm/cli/commands/__init__.py
wasm/cli/commands/backup.py
wasm/cli/commands/cert.py
wasm/cli/commands/config.py
wasm/cli/commands/db.py
wasm/cli/commands/health.py
wasm/cli/commands/monitor.py
wasm/cli/commands/service.py
wasm/cli/commands/setup.py
wasm/cli/commands/site.py
wasm/cli/commands/store.py
wasm/cli/commands/version.py
wasm/cli/commands/web.py
wasm/cli/commands/webapp.py
wasm/completions/__init__.py
wasm/completions/_wasm
wasm/completions/wasm.bash
wasm/completions/wasm.fish
wasm/core/__init__.py
wasm/core/config.py
wasm/core/dependencies.py
wasm/core/exceptions.py
wasm/core/logger.py
wasm/core/store.py
wasm/core/update_checker.py
wasm/core/utils.py
wasm/deployers/__init__.py
wasm/deployers/base.py
wasm/deployers/nextjs.py
wasm/deployers/nodejs.py
wasm/deployers/python.py
wasm/deployers/registry.py
wasm/deployers/static.py
wasm/deployers/vite.py
wasm/deployers/helpers/__init__.py
wasm/deployers/helpers/package_manager.py
wasm/deployers/helpers/path_resolver.py
wasm/deployers/helpers/prisma.py
wasm/managers/__init__.py
wasm/managers/apache_manager.py
wasm/managers/backup_manager.py
wasm/managers/base_manager.py
wasm/managers/cert_manager.py
wasm/managers/nginx_manager.py
wasm/managers/service_manager.py
wasm/managers/source_manager.py
wasm/managers/database/__init__.py
wasm/managers/database/base.py
wasm/managers/database/mongodb.py
wasm/managers/database/mysql.py
wasm/managers/database/postgres.py
wasm/managers/database/redis.py
wasm/managers/database/registry.py
wasm/monitor/__init__.py
wasm/monitor/ai_analyzer.py
wasm/monitor/email_notifier.py
wasm/monitor/process_monitor.py
wasm/monitor/threat_store.py
wasm/templates/__init__.py
wasm/templates/apache/proxy.conf.j2
wasm/templates/apache/static.conf.j2
wasm/templates/nginx/proxy.conf.j2
wasm/templates/nginx/static.conf.j2
wasm/templates/systemd/app.service.j2
wasm/validators/__init__.py
wasm_cli-0.14.0.dist-info/licenses/LICENSE
wasm_cli-0.14.0.dist-info/METADATA
wasm_cli-0.14.0.dist-info/WHEEL
wasm_cli-0.14.0.dist-info/entry_points.txt
wasm_cli-0.14.0.dist-info/top_level.txt
wasm_cli-0.14.0.dist-info/RECORD
