Metadata-Version: 2.4
Name: wasm-cli
Version: 0.14.0
Summary: Web App System Management - Deploy and manage web applications on Linux servers
Author: Yago López Prado
Author-email: Yago López Prado <yago.lopez.adeje@gmail.com>
License: WASM-NCSAL
Project-URL: Homepage, https://github.com/Perkybeet/wasm
Project-URL: Documentation, https://github.com/Perkybeet/wasm#readme
Project-URL: Repository, https://github.com/Perkybeet/wasm.git
Project-URL: Bug Tracker, https://github.com/Perkybeet/wasm/issues
Keywords: cli,deployment,nginx,apache,systemd,web-apps,server-management,certbot,ssl
Classifier: Development Status :: 4 - Beta
Classifier: Environment :: Console
Classifier: Intended Audience :: Developers
Classifier: Intended Audience :: System Administrators
Classifier: License :: Other/Proprietary License
Classifier: Operating System :: POSIX :: Linux
Classifier: Programming Language :: Python :: 3
Classifier: Programming Language :: Python :: 3.10
Classifier: Programming Language :: Python :: 3.11
Classifier: Programming Language :: Python :: 3.12
Classifier: Topic :: System :: Installation/Setup
Classifier: Topic :: System :: Systems Administration
Classifier: Topic :: Internet :: WWW/HTTP :: HTTP Servers
Requires-Python: >=3.10
License-File: LICENSE
Requires-Dist: Jinja2>=3.1.0
Requires-Dist: PyYAML>=6.0
Provides-Extra: interactive
Requires-Dist: inquirer>=3.1.0; extra == "interactive"
Provides-Extra: dev
Requires-Dist: pytest>=7.0; extra == "dev"
Requires-Dist: pytest-cov>=4.0; extra == "dev"
Requires-Dist: black>=23.0; extra == "dev"
Requires-Dist: isort>=5.12; extra == "dev"
Requires-Dist: mypy>=1.0; extra == "dev"
Requires-Dist: ruff>=0.1.0; extra == "dev"
Provides-Extra: rich
Requires-Dist: rich>=13.0; extra == "rich"
Provides-Extra: monitor
Requires-Dist: psutil>=5.9.0; extra == "monitor"
Requires-Dist: httpx>=0.25.0; extra == "monitor"
Provides-Extra: web
Requires-Dist: fastapi>=0.109.0; extra == "web"
Requires-Dist: uvicorn[standard]>=0.27.0; extra == "web"
Requires-Dist: python-jose[cryptography]>=3.3.0; extra == "web"
Requires-Dist: passlib[bcrypt]>=1.7.4; extra == "web"
Requires-Dist: psutil>=5.9.0; extra == "web"
Requires-Dist: aiofiles>=23.0.0; extra == "web"
Provides-Extra: all
Requires-Dist: inquirer>=3.1.0; extra == "all"
Requires-Dist: rich>=13.0; extra == "all"
Requires-Dist: psutil>=5.9.0; extra == "all"
Requires-Dist: httpx>=0.25.0; extra == "all"
Requires-Dist: fastapi>=0.109.0; extra == "all"
Requires-Dist: uvicorn[standard]>=0.27.0; extra == "all"
Requires-Dist: python-jose[cryptography]>=3.3.0; extra == "all"
Requires-Dist: passlib[bcrypt]>=1.7.4; extra == "all"
Requires-Dist: aiofiles>=23.0.0; extra == "all"
Dynamic: author
Dynamic: license-file
Dynamic: requires-python
